[
	{
		"id": 1,
		"name": "Akimoto Manatsu"
	},
	{
		"id": 2,
		"name": "生田 絵梨花"
	},
	{
		"id": 3,
		"name": "齋藤 飛鳥"
	},
	{
		"id": 5,
		"name": "樋口 日奈"
	},
	{
		"id": 6,
		"name": "星野 みなみ"
	},
	{
		"id": 8,
		"name": "和田 まあや"
	},
	{
		"id": 10,
		"name": "北野 日奈子"
	},
	{
		"id": 11,
		"name": "新内 眞衣"
	},
	{
		"id": 12,
		"name": "鈴木 絢音"
	},
	{
		"id": 15,
		"name": "山崎 怜奈"
	},
	{
		"id": 17,
		"name": "伊藤 理々杏"
	},
	{
		"id": 18,
		"name": "岩本 蓮加"
	},
	{
		"id": 19,
		"name": "梅澤 美波"
	},
	{
		"id": 21,
		"name": "久保 史緒里"
	},
	{
		"id": 22,
		"name": "阪口 珠美"
	},
	{
		"id": 23,
		"name": "佐藤 楓"
	},
	{
		"id": 24,
		"name": "中村 麗乃"
	},
	{
		"id": 25,
		"name": "向井 葉月"
	},
	{
		"id": 26,
		"name": "山下 美月"
	},
	{
		"id": 27,
		"name": "吉田 綾乃クリスティー"
	},
	{
		"id": 28,
		"name": "与田 祐希"
	},
	{
		"id": 29,
		"name": "遠藤 さくら"
	},
	{
		"id": 30,
		"name": "賀喜 遥香"
	},
	{
		"id": 31,
		"name": "掛橋 沙耶香"
	},
	{
		"id": 32,
		"name": "金川 紗耶"
	},
	{
		"id": 33,
		"name": "北川 悠理"
	},
	{
		"id": 34,
		"name": "黒見 明香"
	},
	{
		"id": 35,
		"name": "佐藤 璃果"
	},
	{
		"id": 36,
		"name": "柴田 柚菜"
	},
	{
		"id": 37,
		"name": "清宮 レイ"
	},
	{
		"id": 38,
		"name": "田村 真佑"
	},
	{
		"id": 39,
		"name": "筒井 あやめ"
	},
	{
		"id": 40,
		"name": "早川 聖来"
	},
	{
		"id": 41,
		"name": "林 瑠奈"
	},
	{
		"id": 42,
		"name": "松尾 美佑"
	},
	{
		"id": 43,
		"name": "矢久保 美緒"
	},
	{
		"id": 44,
		"name": "弓木 奈於"
	}
]
